qpi/__init__.py
qpi/functions.py
qpi/main.py
qpi/my_exceptions.py
qpi/auth/__init__.py
qpi/auth/auth_module.py
qpi/auth/auth_settings.py
qpi/super_methods/__init__.py
qpi/super_methods/operations.py
qpi/super_methods/super_methods_description.py
qpi/super_methods/tests/__init__.py
qpi/super_methods/tests/test_operations.py
qpi/super_methods/tests/test_super_methods.py
qpi/tests/__init__.py
qpi/tests/main_test.py
qpi/tests/test_core.py
qpi/tests/test_functions.py
qpi/tests/tools.py
qodex_pi-0.23.dist-info/LICENSE
qodex_pi-0.23.dist-info/METADATA
qodex_pi-0.23.dist-info/WHEEL
qodex_pi-0.23.dist-info/top_level.txt
qodex_pi-0.23.dist-info/RECORD
