Metadata-Version: 2.1
Name: qodex-pi
Version: 0.23
Summary: UNKNOWN
Home-page: UNKNOWN
Author: PunchyArchy
Author-email: ksmdrmvscthny@gmail.com
License: UNKNOWN
Platform: UNKNOWN
License-File: LICENSE
Requires-Dist: qsct
Requires-Dist: qodex-dk
